{
  "variant": "dropout",
  "hidden": 16,
  "d_in": 8,
  "cv_rmse": 0.39802954697846316,
  "baseline_rmse": 1.1777286211422064,
  "beats_baseline": true,
  "all_configs": [
    {
      "hidden": 16,
      "variant": "dropout",
      "rmse": 0.39802954697846316
    },
    {
      "hidden": 32,
      "variant": "dropout",
      "rmse": 0.41914846716370735
    },
    {
      "hidden": 32,
      "variant": "ensemble",
      "rmse": 0.42322045215083876
    },
    {
      "hidden": 16,
      "variant": "ensemble",
      "rmse": 0.43189519322734815
    },
    {
      "hidden": 32,
      "variant": "wd",
      "rmse": 0.43234592691414436
    },
    {
      "hidden": 32,
      "variant": "plain",
      "rmse": 0.4363596297140167
    },
    {
      "hidden": 16,
      "variant": "wd",
      "rmse": 0.48760815583027517
    },
    {
      "hidden": 16,
      "variant": "plain",
      "rmse": 0.49476641266141536
    }
  ],
  "gradient_at_best": [
    -0.5532721281051636,
    -0.213262677192688,
    -0.7757005095481873,
    -0.1660856455564499,
    0.05231190845370293,
    0.01550255250185728,
    -0.4763377606868744,
    0.11111609637737274
  ],
  "x_best": [
    0.155378,
    0.200562,
    0.075482,
    0.215712,
    0.672482,
    0.740636,
    0.179584,
    0.616336
  ],
  "y_best": 9.9111789172124,
  "y_mean": 8.22432333744923,
  "y_std": 1.1777286311422064,
  "n_ensemble": 1
}